visualizr/__init__.py
visualizr/__main__.py
visualizr/anitalker/__init__.py
visualizr/anitalker/checkpoint.py
visualizr/anitalker/choices.py
visualizr/anitalker/config.py
visualizr/anitalker/config_base.py
visualizr/anitalker/diffusion/__init__.py
visualizr/anitalker/diffusion/base.py
visualizr/anitalker/diffusion/diffusion.py
visualizr/anitalker/diffusion/resample.py
visualizr/anitalker/experiment.py
visualizr/anitalker/face_sr/__init__.py
visualizr/anitalker/face_sr/face_enhancer.py
visualizr/anitalker/face_sr/videoio.py
visualizr/anitalker/liamodel.py
visualizr/anitalker/model/__init__.py
visualizr/anitalker/model/blocks.py
visualizr/anitalker/model/latentnet.py
visualizr/anitalker/model/nn.py
visualizr/anitalker/model/seq2seq.py
visualizr/anitalker/model/unet.py
visualizr/anitalker/model/unet_autoenc.py
visualizr/anitalker/networks/__init__.py
visualizr/anitalker/networks/discriminator.py
visualizr/anitalker/networks/encoder.py
visualizr/anitalker/networks/styledecoder.py
visualizr/anitalker/renderer.py
visualizr/anitalker/templates.py
visualizr/anitalker/utils.py
visualizr/app/__init__.py
visualizr/app/builder.py
visualizr/app/logger.py
visualizr/app/runner.py
visualizr/app/settings.py
visualizr/app/types.py
visualizr-0.1.0.dist-info/WHEEL
visualizr-0.1.0.dist-info/entry_points.txt
visualizr-0.1.0.dist-info/METADATA
visualizr-0.1.0.dist-info/RECORD
